pc_price_prediction/__init__.py
pc_price_prediction/algorithm.py
pc_price_prediction-0.0.1.dist-info/licenses/LICENSE.txt
pc_price_prediction-0.0.1.dist-info/METADATA
pc_price_prediction-0.0.1.dist-info/WHEEL
pc_price_prediction-0.0.1.dist-info/top_level.txt
pc_price_prediction-0.0.1.dist-info/RECORD
